chq/__init__.py
chq/getflaggg.py
chq-1.0.dist-info/LICENSE
chq-1.0.dist-info/METADATA
chq-1.0.dist-info/WHEEL
chq-1.0.dist-info/top_level.txt
chq-1.0.dist-info/RECORD
