Metadata-Version: 2.1
Name: chq
Version: 1.0
Summary: Hacktool
Home-page: https://github.com/tangyi19/chq
Author: TangYi
Author-email: adamtang0830@gmail.com
License: UNKNOWN
Platform: UNKNOWN
Classifier: Programming Language :: Python :: 3
Classifier: License :: OSI Approved :: MIT License
Classifier: Operating System :: OS Independent
Requires-Dist: hashlib
